kedro_viz/__init__.py
kedro_viz/autoreload_file_filter.py
kedro_viz/constants.py
kedro_viz/server.py
kedro_viz/utils.py
kedro_viz/api/__init__.py
kedro_viz/api/apps.py
kedro_viz/api/rest/__init__.py
kedro_viz/api/rest/requests.py
kedro_viz/api/rest/router.py
kedro_viz/api/rest/utils.py
kedro_viz/api/rest/responses/__init__.py
kedro_viz/api/rest/responses/base.py
kedro_viz/api/rest/responses/metadata.py
kedro_viz/api/rest/responses/nodes.py
kedro_viz/api/rest/responses/pipelines.py
kedro_viz/api/rest/responses/run_events.py
kedro_viz/api/rest/responses/save_responses.py
kedro_viz/api/rest/responses/utils.py
kedro_viz/api/rest/responses/version.py
kedro_viz/data_access/__init__.py
kedro_viz/data_access/managers.py
kedro_viz/data_access/repositories/__init__.py
kedro_viz/data_access/repositories/catalog.py
kedro_viz/data_access/repositories/graph.py
kedro_viz/data_access/repositories/modular_pipelines.py
kedro_viz/data_access/repositories/registered_pipelines.py
kedro_viz/data_access/repositories/tags.py
kedro_viz/html/404.html
kedro_viz/html/autoreload.html
kedro_viz/html/favicon.ico
kedro_viz/html/index.html
kedro_viz/html/telemetry.html
kedro_viz/html/.vite/manifest.json
kedro_viz/html/assets/_baseUniq-CCXjGrM5.js
kedro_viz/html/assets/arc-COiBpiu4.js
kedro_viz/html/assets/architectureDiagram-VXUJARFQ-BjzbyiTA.js
kedro_viz/html/assets/blockDiagram-VD42YOAC-CaaPf_-e.js
kedro_viz/html/assets/c4Diagram-YG6GDRKO-vwy3uKMD.js
kedro_viz/html/assets/channel-B7pgA2u4.js
kedro_viz/html/assets/chunk-4BX2VUAB-nM8iefwB.js
kedro_viz/html/assets/chunk-55IACEB6-cacOl2G_.js
kedro_viz/html/assets/chunk-B4BG7PRW-DWmO5jYn.js
kedro_viz/html/assets/chunk-DI55MBZ5-CXs9u0lU.js
kedro_viz/html/assets/chunk-FMBD7UC4-X3IJf3a-.js
kedro_viz/html/assets/chunk-QN33PNHL-Bs-J6BNd.js
kedro_viz/html/assets/chunk-QZHKN3VN-Cggvb10h.js
kedro_viz/html/assets/chunk-TZMSLE5B-Zg1noD__.js
kedro_viz/html/assets/classDiagram-2ON5EDUG-DJfgB0Nn.js
kedro_viz/html/assets/classDiagram-v2-WZHVMYZB-DJfgB0Nn.js
kedro_viz-12.3.0.dist-info/METADATA
kedro_viz-12.3.0.dist-info/WHEEL
kedro_viz-12.3.0.dist-info/entry_points.txt
kedro_viz-12.3.0.dist-info/RECORD
