Metadata-Version: 2.4
Name: kedro-viz
Version: 12.3.0
Summary: Kedro-Viz helps visualise Kedro data and analytics pipelines
Project-URL: Homepage, https://kedro.org
Project-URL: Source, https://github.com/kedro-org/kedro-viz
Project-URL: Documentation, https://docs.kedro.org/projects/kedro-viz
Project-URL: Tracker, https://github.com/kedro-org/kedro-viz/issues
Author: Kedro
License: Apache Software License (Apache 2.0)
Keywords: data engineering,data pipelines,data science,machine learning,pipelines,visualisation
Requires-Python: >=3.10
Requires-Dist: aiofiles>=22.1.0
Requires-Dist: click-default-group
Requires-Dist: fastapi<0.200.0,>=0.100.0
Requires-Dist: fsspec>=2021.4
Requires-Dist: ipython<9.0,>=7.0.0
Requires-Dist: kedro-telemetry>=0.6.0
Requires-Dist: kedro>=1.0.0
Requires-Dist: networkx>=2.5
Requires-Dist: orjson<4.0,>=3.9
Requires-Dist: packaging>=23.0
Requires-Dist: pandas>=1.3
Requires-Dist: pathspec>=0.12.1
Requires-Dist: plotly>=4.0
Requires-Dist: pydantic>=2.0.0
Requires-Dist: secure>=0.3.0
Requires-Dist: uvicorn[standard]<1.0,>=0.30.0
Requires-Dist: watchfiles>=0.24.0
Requires-Dist: werkzeug>=3.0.0
Provides-Extra: aws
Requires-Dist: s3fs>=2021.4; extra == 'aws'
Provides-Extra: azure
Requires-Dist: adlfs>=2021.4; extra == 'azure'
Provides-Extra: docs
Requires-Dist: linkchecker>=10.2.1; extra == 'docs'
Requires-Dist: mkdocs-autorefs>=1.4.1; extra == 'docs'
Requires-Dist: mkdocs-get-deps>=0.2.0; extra == 'docs'
Requires-Dist: mkdocs-llmstxt; extra == 'docs'
Requires-Dist: mkdocs-material-extensions>=1.3.1; extra == 'docs'
Requires-Dist: mkdocs-material>=9.6.11; extra == 'docs'
Requires-Dist: mkdocs-mermaid2-plugin>=1.2.1; extra == 'docs'
Requires-Dist: mkdocs>=1.6.1; extra == 'docs'
Requires-Dist: mkdocstrings-python>=0.29.1; extra == 'docs'
Requires-Dist: mkdocstrings>=0.29.1; extra == 'docs'
Provides-Extra: gcp
Requires-Dist: gcsfs>=2021.4; extra == 'gcp'
